json_ntv/__init__.py
json_ntv/namespace.py
json_ntv/ntv.py
json_ntv/ntv_comment.py
json_ntv/ntv_connector.py
json_ntv/ntv_patch.py
json_ntv/ntv_util.py
json_ntv/ntv_validate.py
json_ntv/config/NTV_fr_BAN_namespace.ini
json_ntv/config/NTV_fr_BAN_test_namespace.ini
json_ntv/config/NTV_fr_IRVE_namespace.ini
json_ntv/config/NTV_fr_namespace.ini
json_ntv/config/NTV_global_namespace.ini
json_ntv/config/NTV_sch_namespace.ini
json_ntv/config/NTV_schemaorg_namespace.ini
json_ntv-1.4.0.dist-info/METADATA
json_ntv-1.4.0.dist-info/WHEEL
json_ntv-1.4.0.dist-info/top_level.txt
json_ntv-1.4.0.dist-info/RECORD
