Metadata-Version: 2.1
Name: json_ntv
Version: 1.4.0
Summary: JSON-NTV a semantic format for interoperability
Home-page: https://github.com/loco-philippe/NTV/blob/main/README.md
Author: Philippe Thomy
Author-email: philippe@loco-labs.io
Keywords: JSON-NTV,semantic JSON,development,environmental data
Classifier: Development Status :: 5 - Production/Stable
Classifier: Intended Audience :: Developers
Classifier: Topic :: Software Development :: Build Tools
Classifier: License :: OSI Approved :: MIT License
Classifier: Programming Language :: Python :: 3
Requires-Python: >=3.7, <4
Requires-Dist: shapely
Requires-Dist: cbor2
Requires-Dist: tab-dataset
